README.md
setup.py
toggle_admin/__init__.py
toggle_admin.egg-info/PKG-INFO
toggle_admin.egg-info/SOURCES.txt
toggle_admin.egg-info/dependency_links.txt
toggle_admin.egg-info/requires.txt
toggle_admin.egg-info/top_level.txt
toggle_admin/http/__init__.py
toggle_admin/http/requests.py
toggle_admin/src/__init__.py
toggle_admin/src/core.py
toggle_admin/src/exceptions.py