Metadata-Version: 2.1
Name: toggle-admin
Version: 0.2
Summary: Asynchronous module for issuing admin permissions
Home-page: https://github.com/zpodushkin/toggle-admin
Author: zpodushkin
Author-email: 
License: GPL-3.0
Platform: UNKNOWN
Classifier: Programming Language :: Python :: 3.5
Classifier: Programming Language :: Python :: 3.6
Classifier: Programming Language :: Python :: 3.7
Classifier: Operating System :: OS Independent
